{
  "$schema": "https://developer.microsoft.com/json-schemas/fabric/item/report/definition/visualContainer/1.6.0/schema.json",
  "name": "037df3c8cbd6e8d4f23f",
  "position": {
    "x": 470.44190769661742,
    "y": 447.493521955319,
    "z": 11,
    "height": 227.57149193454256,
    "width": 229.48385741298412,
    "tabOrder": 10
  },
  "visual": {
    "visualType": "card",
    "query": {
      "queryState": {
        "Values": {
          "projections": [
            {
              "field": {
                "Measure": {
                  "Expression": {
                    "SourceRef": {
                      "Entity": "Measures Table"
                    }
                  },
                  "Property": "value example"
                }
              },
              "queryRef": "Measures Table.value example",
              "nativeQueryRef": "value example"
            }
          ]
        }
      },
      "sortDefinition": {
        "sort": [
          {
            "field": {
              "Measure": {
                "Expression": {
                  "SourceRef": {
                    "Entity": "Measures Table"
                  }
                },
                "Property": "value example"
              }
            },
            "direction": "Descending"
          }
        ],
        "isDefaultSort": true
      }
    },
    "drillFilterOtherVisuals": true
  }
}